eb_short.py
eb_short-0.0.5.dist-info/LICENSE
eb_short-0.0.5.dist-info/METADATA
eb_short-0.0.5.dist-info/WHEEL
eb_short-0.0.5.dist-info/entry_points.txt
eb_short-0.0.5.dist-info/top_level.txt
eb_short-0.0.5.dist-info/RECORD
