Metadata-Version: 2.1
Name: eb-short
Version: 0.0.5
Summary: earlybtyte link shortener
Home-page: https://www.earlybyte.ch
Author: Remo Hoeppli
Author-email: remo.hoeppli@earlybyte.ch
License: MIT License
Platform: UNKNOWN
Classifier: Programming Language :: Python :: 3.7
Classifier: Operating System :: OS Independent
Requires-Python: >=3.7
License-File: LICENSE
Requires-Dist: setuptools
Requires-Dist: typer (>=0.6.1)
Requires-Dist: requests (>=2.28.1)
